nonebot_plugin_obastatus/__init__.py
nonebot_plugin_obastatus/config.py
nonebot_plugin_obastatus-1.0.7.dist-info/LICENSE
nonebot_plugin_obastatus-1.0.7.dist-info/METADATA
nonebot_plugin_obastatus-1.0.7.dist-info/WHEEL
nonebot_plugin_obastatus-1.0.7.dist-info/top_level.txt
nonebot_plugin_obastatus-1.0.7.dist-info/RECORD
