Metadata-Version: 2.1
Name: nonebot_plugin_obastatus
Version: 1.0.7
Summary: 获取 OpenBMCLAPI 相关数据
Requires-Python: <4.0,>=3.8
License-File: LICENSE
Requires-Dist: nonebot2 <3.0.0,>=2.2.0
Requires-Dist: httpx <1.0.0,>=0.27.0
Requires-Dist: loguru <1.0.0,>=0.7.2
Requires-Dist: aiofiles <24.0.0,>=23.2.1
Requires-Dist: nonebot-plugin-send-anything-anywhere <1.0.0,>=0.6.1
Requires-Dist: nonebot-plugin-apscheduler <1.0.0,>=0.3.0
Requires-Dist: nonebot-plugin-localstore <1.0.0,>=0.6.0
